password_policy_compliance/__init__.py
password_policy_compliance/blacklist_checker.py
password_policy_compliance/compliance_reporter.py
password_policy_compliance/password_expiration.py
password_policy_compliance/password_generator.py
password_policy_compliance/password_strength.py
password_policy_compliance/password_validator.py
password_policy_compliance/policy_compliance.py
password_policy_compliance/examples/__init__.py
password_policy_compliance/examples/basic_usage.py
password_policy_compliance/examples/password_management_system.py
password_policy_compliance/examples/web_app_integration.py
password_policy_compliance-0.2.0.dist-info/LICENSE
password_policy_compliance-0.2.0.dist-info/METADATA
password_policy_compliance-0.2.0.dist-info/WHEEL
password_policy_compliance-0.2.0.dist-info/top_level.txt
password_policy_compliance-0.2.0.dist-info/RECORD
