Metadata-Version: 2.1
Name: password_policy_compliance
Version: 0.2.0
Summary: A Python library for enforcing password policies and compliance
Home-page: https://github.com/bassemabidi/password_policy_compliance
Author: Bassem Abidi
Author-email: abidi.bassem@me.com
License: MIT
Classifier: Development Status :: 3 - Alpha
Classifier: Intended Audience :: Developers
Classifier: License :: OSI Approved :: MIT License
Classifier: Operating System :: OS Independent
Classifier: Programming Language :: Python :: 3
Classifier: Programming Language :: Python :: 3.6
Classifier: Programming Language :: Python :: 3.7
Classifier: Programming Language :: Python :: 3.8
Classifier: Programming Language :: Python :: 3.9
Requires-Python: >=3.6
License-File: LICENSE
Requires-Dist: requests<3.0.0,>=2.25.1
Requires-Dist: zxcvbn<5.0.0,>=4.4.28
Requires-Dist: flask<3.0.0,>=2.0.0
Provides-Extra: dev
Requires-Dist: pytest; extra == "dev"
Requires-Dist: pytest-cov; extra == "dev"
